scopey/__init__.py
scopey/config.py
scopey/py.typed
scopey/utils.py
scopey-1.1.1.dist-info/licenses/LICENSE
scopey-1.1.1.dist-info/METADATA
scopey-1.1.1.dist-info/WHEEL
scopey-1.1.1.dist-info/top_level.txt
scopey-1.1.1.dist-info/RECORD
