Metadata-Version: 2.4
Name: scopey
Version: 1.1.1
Summary: Scope Configuration for Python
Author-email: C4C-Dev <jerry.sy.bai@gmail.com>
Requires-Python: >=3.9
License-File: LICENSE
Requires-Dist: tomlkit
Requires-Dist: pytest
Requires-Dist: flake8
Requires-Dist: black
Requires-Dist: isort
Dynamic: license-file
